{
    "scriptName": "GenerateDispose",
    "steps":
[
    {"typeStep":"exec","arg":"clipchamp.exe launch"},
    {"typeStep":"text","arg": "Welcome to Roslyn Examples"},
    {"typeStep":"text","arg":"If you want to see more examples , see  List Of RSCG"},
    {"typeStep":"browser","arg":"https://ignatandrei.github.io/RSCG_Examples/v2/docs/List-of-RSCG"},
    {"typeStep":"text","arg": "My name is Andrei Ignat and I am deeply fond of Roslyn Source Code Generator. "},

{"typeStep":"text","arg": "Today I will present GenerateDispose . GenerateDispose for boilerplate reduction for IDisposable pattern### PurposeA Roslyn source generator that replaces the 10+ lines of IDisposable boilerplate code with a single attribute.It also automatically adapts the generated pattern when the class modifiers change (e.g. sealed to non-sealed).### How to Define```csharp showLineNumbers[GenerateDispose.SourceGenerators.GenerateDispose(nameof(Drop))]partial class DALDB : IDisposable   // : IDisposable is optional!{    private ConnectionDB cn;    private ConnectionDB cn1;    public DALDB()    {        cn = new ConnectionDB();        cn1 = new ConnectionDB();    }    public void Drop()   // Your custom disposal logic    {        cn.Dispose();        cn1.Dispose();    }}```- The class must be partial- Pass nameof(YourDisposeMethod) to the attribute - the method must be callable with no arguments### What Gets Generated- public void Dispose() (thread-safe, calls your method)- A private int _isDisposed field for double-dispose protection- Adapts to sealed vs non-sealed automatically (private vs protected virtual)### How to Use```csharp showLineNumbersusing (var db = new DALDB()){    // use db...}  // Dispose() called automatically```### Key Benefits- 10+ lines of boilerplate replaced by 1 attribute- sealed changes auto-adapt the Dispose pattern- No manual IDisposable wiring needed ."},
{"typeStep":"browser","arg":"https://www.nuget.org/packages/GenerateDispose/"},
{"typeStep":"text","arg": "The whole example is here"},
{"typeStep":"browser","arg":"https://ignatandrei.github.io/RSCG_Examples/v2/docs/GenerateDispose"},
{"typeStep":"text","arg": "You can download the code from here"},
{"typeStep":"browser","arg":"https://ignatandrei.github.io/RSCG_Examples/v2/docs/GenerateDispose#download-example-net--c-"},
{"typeStep":"text","arg":"Here is the code downloaded "},
{"typeStep":"exec","arg":"explorer.exe /select,D:\\gth\\RSCG_Examples\\v2\\rscg_examples\\GenerateDispose\\src\\IDisp.sln"},
{"typeStep":"text","arg": "So , let's start the project with Visual Studio Code "},
{"typeStep":"stepvscode","arg": "-n D:\\gth\\RSCG_Examples\\v2\\rscg_examples\\GenerateDispose\\src"},

{"typeStep":"text","arg": "To use it ,you will put the Nuget GenerateDispose into the csproj "},

{"typeStep":"stepvscode","arg": "-r -g D:\\gth\\RSCG_Examples\\v2\\rscg_examples\\GenerateDispose\\src\\IDisp\\IDisp.csproj"},

{"typeStep":"text","arg": "And now I will show you an example of using GenerateDispose"},

{"typeStep":"hide","arg": "now execute the tour in VSCode"},
{"typeStep":"tour", "arg": "src/.tours/"},
{"typeStep":"text","arg":" And I will execute the project"}, 
{"typeStep":"showproj", "arg":"IDisp.csproj"},
{"typeStep":"text","arg":" This concludes the project"},
{"typeStep":"waitseconds","arg":"30"},
{"typeStep":"text","arg": "Remember, you can download the code from here"},
{"typeStep":"browser","arg":"https://ignatandrei.github.io/RSCG_Examples/v2/docs/GenerateDispose#download-example-net--c-",
SpeakTest=" "},
{"typeStep":"waitseconds","arg":"30"},
]
}
